escloud_mcp_server/__init__.py
escloud_mcp_server/__main__.py
escloud_mcp_server/client.py
escloud_mcp_server/server.py
escloud_mcp_server/tools/instance_info.py
escloud_mcp_server/tools/resource_info.py
escloud_mcp_server-0.0.2.dist-info/METADATA
escloud_mcp_server-0.0.2.dist-info/WHEEL
escloud_mcp_server-0.0.2.dist-info/entry_points.txt
escloud_mcp_server-0.0.2.dist-info/RECORD
