Metadata-Version: 2.4
Name: escloud-mcp-server
Version: 0.0.2
Summary: ESCloud MCP Server
License-Expression: MIT
Requires-Python: >=3.10
Requires-Dist: mcp[cli]>=1.6.0
Requires-Dist: volcengine-python-sdk>=1.1.3
